TikExt/__init__.py
TikExt/core.py
tikext-1.0.0.dist-info/licenses/LICENSE
tikext-1.0.0.dist-info/METADATA
tikext-1.0.0.dist-info/WHEEL
tikext-1.0.0.dist-info/top_level.txt
tikext-1.0.0.dist-info/RECORD
