Metadata-Version: 2.4
Name: TikExt
Version: 1.0.0
Summary: مكتبة شاملة للتفاعل مع TikTok API
Author: Mustafa
Author-email: tofey.amrie@gmail.com
Project-URL: Source, https://github.com/yourusername/TikExt
Project-URL: Bug Reports, https://github.com/yourusername/TikExt/issues
Keywords: tiktok api social media automation
Classifier: Programming Language :: Python :: 3
Classifier: License :: OSI Approved :: MIT License
Classifier: Operating System :: OS Independent
Requires-Python: >=3.6
License-File: LICENSE
Requires-Dist: faker
Requires-Dist: requests
Requires-Dist: user_agent
Requires-Dist: SignerPy
Dynamic: author
Dynamic: author-email
Dynamic: classifier
Dynamic: description
Dynamic: description-content-type
Dynamic: keywords
Dynamic: license-file
Dynamic: project-url
Dynamic: requires-dist
Dynamic: requires-python
Dynamic: summary
